doctra/__init__.py
doctra/version.py
doctra/cli/__init__.py
doctra/cli/main.py
doctra/cli/utils.py
doctra/engines/__init__.py
doctra/engines/image_restoration/__init__.py
doctra/engines/image_restoration/docres_engine.py
doctra/engines/layout/__init__.py
doctra/engines/layout/layout_models.py
doctra/engines/layout/paddle_layout.py
doctra/engines/ocr/__init__.py
doctra/engines/ocr/api.py
doctra/engines/ocr/paddleocr_engine.py
doctra/engines/ocr/path_resolver.py
doctra/engines/ocr/pytesseract_engine.py
doctra/engines/vlm/__init__.py
doctra/engines/vlm/outlines_types.py
doctra/engines/vlm/provider.py
doctra/engines/vlm/service.py
doctra/exporters/__init__.py
doctra/exporters/excel_writer.py
doctra/exporters/html_writer.py
doctra/exporters/image_saver.py
doctra/exporters/markdown_table.py
doctra/exporters/markdown_writer.py
doctra/parsers/__init__.py
doctra/parsers/docx_utils.py
doctra/parsers/enhanced_pdf_parser.py
doctra/parsers/layout_order.py
doctra/parsers/paddleocr_vl_parser.py
doctra/parsers/split_table_detector.py
doctra/parsers/structured_docx_parser.py
doctra/parsers/structured_pdf_parser.py
doctra/parsers/table_chart_extractor.py
doctra/third_party/docres/inference.py
doctra/third_party/docres/utils.py
doctra/third_party/docres/data/MBD/MBD.py
doctra/third_party/docres/data/MBD/MBD_utils.py
doctra/third_party/docres/data/MBD/infer.py
doctra/third_party/docres/data/MBD/model/deep_lab_model/aspp.py
doctra/third_party/docres/data/MBD/model/deep_lab_model/decoder.py
doctra/third_party/docres/data/MBD/model/deep_lab_model/deeplab.py
doctra/third_party/docres/data/MBD/model/deep_lab_model/backbone/__init__.py
doctra/third_party/docres/data/MBD/model/deep_lab_model/backbone/drn.py
doctra/third_party/docres/data/MBD/model/deep_lab_model/backbone/mobilenet.py
doctra/third_party/docres/data/MBD/model/deep_lab_model/backbone/resnet.py
doctra/third_party/docres/data/MBD/model/deep_lab_model/backbone/xception.py
doctra-0.9.7.dist-info/licenses/LICENSE
doctra-0.9.7.dist-info/METADATA
doctra-0.9.7.dist-info/WHEEL
doctra-0.9.7.dist-info/entry_points.txt
doctra-0.9.7.dist-info/top_level.txt
doctra-0.9.7.dist-info/RECORD
