Metadata-Version: 2.4
Name: doctra
Version: 0.9.7
Summary: Parse, extract, and analyze documents with ease
Home-page: https://github.com/AdemBoukhris457/Doctra
Author: Adem Boukhris
Author-email: Adem Boukhris <boukhrisadam98@gmail.com>
License:                                  Apache License
Project-URL: Homepage, https://github.com/AdemBoukhris457/Doctra
Project-URL: Repository, https://github.com/AdemBoukhris457/Doctra
Project-URL: Issues, https://github.com/AdemBoukhris457/Doctra/issues
Keywords: pdf,parser,document,extraction,ocr,layout-detection
Classifier: Development Status :: 4 - Beta
Classifier: Intended Audience :: Developers
Classifier: License :: OSI Approved :: MIT License
Classifier: Operating System :: OS Independent
Classifier: Programming Language :: Python :: 3
Classifier: Programming Language :: Python :: 3.8
Classifier: Programming Language :: Python :: 3.9
Classifier: Programming Language :: Python :: 3.10
Classifier: Programming Language :: Python :: 3.11
Classifier: Programming Language :: Python :: 3.12
Classifier: Topic :: Software Development :: Libraries :: Python Modules
Classifier: Topic :: Text Processing :: Markup
Classifier: Topic :: Multimedia :: Graphics :: Graphics Conversion
Requires-Python: >=3.8
License-File: LICENSE
Requires-Dist: paddlepaddle>=2.4.0
Requires-Dist: paddleocr>=2.6.0
Requires-Dist: pillow>=8.0.0
Requires-Dist: opencv-python>=4.5.0
Requires-Dist: pandas>=1.3.0
Requires-Dist: openpyxl>=3.0.0
Requires-Dist: tesseract>=0.1.3
Requires-Dist: pytesseract>=0.3.10
Requires-Dist: pdf2image>=1.16.0
Requires-Dist: anthropic>=0.40.0
Requires-Dist: outlines>=0.0.34
Requires-Dist: tqdm>=4.62.0
Requires-Dist: matplotlib>=3.5.0
Requires-Dist: click>=8.0.0
Requires-Dist: python-docx>=0.8.11
Requires-Dist: google-genai
Requires-Dist: openai>=1.0.0
Requires-Dist: ollama>=0.1.0
Requires-Dist: markdown-it-py>=2.0.0
Requires-Dist: gradio
Requires-Dist: pymupdf>=1.23.0
Requires-Dist: scikit-image>=0.19.3
Requires-Dist: torchvision
Provides-Extra: openai
Requires-Dist: openai>=1.0.0; extra == "openai"
Provides-Extra: gemini
Requires-Dist: google-genai; extra == "gemini"
Provides-Extra: dev
Requires-Dist: pytest>=6.0; extra == "dev"
Requires-Dist: pytest-cov>=2.0; extra == "dev"
Requires-Dist: black>=21.0; extra == "dev"
Requires-Dist: isort>=5.0; extra == "dev"
Requires-Dist: flake8>=3.9; extra == "dev"
Requires-Dist: mypy>=0.910; extra == "dev"
Requires-Dist: pre-commit>=2.15.0; extra == "dev"
Dynamic: author
Dynamic: home-page
Dynamic: license-file
Dynamic: requires-python
